datawrapper_mcp/__init__.py
datawrapper_mcp/__main__.py
datawrapper_mcp/config.py
datawrapper_mcp/py.typed
datawrapper_mcp/server.py
datawrapper_mcp/types.py
datawrapper_mcp/utils.py
datawrapper_mcp/handlers/__init__.py
datawrapper_mcp/handlers/create.py
datawrapper_mcp/handlers/delete.py
datawrapper_mcp/handlers/export.py
datawrapper_mcp/handlers/publish.py
datawrapper_mcp/handlers/retrieve.py
datawrapper_mcp/handlers/schema.py
datawrapper_mcp/handlers/update.py
datawrapper_mcp-0.0.15.dist-info/licenses/LICENSE
datawrapper_mcp-0.0.15.dist-info/METADATA
datawrapper_mcp-0.0.15.dist-info/WHEEL
datawrapper_mcp-0.0.15.dist-info/entry_points.txt
datawrapper_mcp-0.0.15.dist-info/top_level.txt
datawrapper_mcp-0.0.15.dist-info/RECORD
