Metadata-Version: 2.4
Name: datawrapper-mcp
Version: 0.0.15
Summary: A Model Context Protocol (MCP) server for creating Datawrapper charts using AI assistants
Author-email: Ben Welsh <b@palewi.re>
License: MIT
Project-URL: Maintainer, https://github.com/palewire/
Project-URL: Source, https://github.com/palewire/datawrapper-mcp/
Project-URL: Issues, https://github.com/palewire/datawrapper-mcp/issues/
Keywords: datawrapper,mcp,model-context-protocol,charts,visualization,ai
Classifier: Development Status :: 5 - Production/Stable
Classifier: Programming Language :: Python
Classifier: Programming Language :: Python :: 3
Classifier: Programming Language :: Python :: 3.10
Classifier: Programming Language :: Python :: 3.11
Classifier: Programming Language :: Python :: 3.12
Classifier: Programming Language :: Python :: 3.13
Classifier: License :: OSI Approved :: MIT License
Classifier: Intended Audience :: Developers
Classifier: Typing :: Typed
Requires-Python: >=3.10
License-File: LICENSE
Requires-Dist: datawrapper>=2.0.14
Requires-Dist: mcp[cli]>=1.20.0
Requires-Dist: pandas>=2.0.0
Requires-Dist: exceptiongroup; python_version < "3.11"
Requires-Dist: typing_extensions>=4.0.0; python_version < "3.11"
Provides-Extra: dev
Requires-Dist: pre-commit; extra == "dev"
Requires-Dist: setuptools-scm; extra == "dev"
Provides-Extra: test
Requires-Dist: pytest>=7.0.0; extra == "test"
Requires-Dist: pytest-asyncio>=0.21.0; extra == "test"
Requires-Dist: pytest-runner; extra == "test"
Requires-Dist: pytest-cov; extra == "test"
Requires-Dist: pytest-env; extra == "test"
Requires-Dist: pytest-vcr; extra == "test"
Requires-Dist: pytest-xdist; extra == "test"
Provides-Extra: mypy
Requires-Dist: mypy; extra == "mypy"
Requires-Dist: pandas-stubs; extra == "mypy"
Requires-Dist: types-requests; extra == "mypy"
Dynamic: license-file
